setup.cfg
setup.py
./__init__.py
./address.py
./sale.py
./sale.xml
./shipment.py
./tryton.cfg
./tests/__init__.py
./tests/test_address.py
./tests/test_sale.py
./tests/test_views_depends.py
./view/sale_channel_form.xml
./view/sale_configuration_view_form.xml
./view/sale_line_form.xml
./view/sale_view_form.xml
fio_pos.egg-info/PKG-INFO
fio_pos.egg-info/SOURCES.txt
fio_pos.egg-info/dependency_links.txt
fio_pos.egg-info/entry_points.txt
fio_pos.egg-info/not-zip-safe
fio_pos.egg-info/requires.txt
fio_pos.egg-info/top_level.txt